{
  "$schema": "https://mintlify.com/docs.json",
  "name": "terraform-aws-wafv2",
  "theme": "aspen",
  "colors": {
    "primary": "#594ed8",
    "light": "#acacf4",
    "dark": "#040404"
  },
  "favicon": "/favicon.svg",
  "logo": {
    "light": "https://media.brand.dev/448fe42e-e2e3-494e-ae00-baff79ebb002.png",
    "dark": "https://media.brand.dev/e17d026d-572d-467c-9d7d-22530830489c.png"
  },
  "navbar": {
    "primary": {
      "type": "github",
      "href": "https://github.com/trussworks/terraform-aws-wafv2"
    }
  },
  "footer": {
    "socials": {
      "github": "https://github.com/trussworks/terraform-aws-wafv2"
    }
  },
  "navigation": {
    "tabs": [
      {
        "tab": "Documentation",
        "groups": [
          {
            "group": "Get Started",
            "pages": ["introduction", "quickstart"]
          },
          {
            "group": "Guides",
            "pages": [
              "guides/cloudfront",
              "guides/alb",
              "guides/ip-blocking",
              "guides/rate-limiting",
              "guides/logging",
              "guides/managed-rules"
            ]
          },
          {
            "group": "Security",
            "pages": [
              "security/overview",
              "security/rule-groups"
            ]
          }
        ]
      },
      {
        "tab": "Reference",
        "groups": [
          {
            "group": "Module Reference",
            "pages": [
              "reference/inputs",
              "reference/outputs",
              "reference/resources"
            ]
          },
          {
            "group": "Examples",
            "pages": [
              "reference/examples"
            ]
          }
        ]
      }
    ]
  }
}
